{
  "project_info": {
    "project_number": "544692371717",
    "project_id": "noteapp-df285",
    "storage_bucket": "noteapp-df285.appspot.com"
  },
  "client": [
    {
      "client_info": {
        "mobilesdk_app_id": "1:544692371717:android:080b9077286ca6cb5fb76c",
        "android_client_info": {
          "package_name": "com.example.noteapp"
        }
      },
      "oauth_client": [
        {
          "client_id": "544692371717-ujp27stni2at0aee6oriuqb7at5eqptv.apps.googleusercontent.com",
          "client_type": 1,
          "android_info": {
            "package_name": "com.example.noteapp",
            "certificate_hash": "b895ccf00780774d56fa4ed0a7a046af6fe30467"
          }
        },
        {
          "client_id": "544692371717-m8q7h27c84o3tamba9kk1bsv8jtahdlh.apps.googleusercontent.com",
          "client_type": 3
        }
      ],
      "api_key": [
        {
          "current_key": "AIzaSyDtlMd6LBuFYYqKsJkMdDGEBHDCne9caMQ"
        }
      ],
      "services": {
        "appinvite_service": {
          "other_platform_oauth_client": [
            {
              "client_id": "544692371717-m8q7h27c84o3tamba9kk1bsv8jtahdlh.apps.googleusercontent.com",
              "client_type": 3
            }
          ]
        }
      }
    }
  ],
  "configuration_version": "1"
}